{
	"definitions": [
		{
			"title": "Login",
			"id": "login",
			"plugins": {
				"xwalk": {
					"page": {
						"resourceType": "core/franklin/components/block/v1/block",
						"template": {
							"name": "Login",
							"model": "login",
							"filter": "login"
						}
					}
				}
			}
		},
		{
			"title": "Login Link",
			"id": "login-link",
			"plugins": {
				"xwalk": {
					"page": {
						"resourceType": "core/franklin/components/block/v1/block/item",
						"template": {
							"name": "Login Link",
							"model": "login-link",
							"filter": "login-link"
						}
					}
				}
			}
		}
	],
	"models": [
		{
			"id": "login",
			"fields": [
				{
					"component": "text",
					"name": "linkText",
					"label": "Text",
					"description": "Button label text",
					"required": true
				}
			]
		},
		{
			"id": "login-link",
			"fields": [
				{
          "component": "richtext",
          "name": "text",
          "value": "",
          "label": "Text",
          "valueType": "string"
        }
			]
		}
	],
	"filters": [
		{
			"id": "login",
			"components": [
				"login-link"
			]
		}
	]
}